nonebot_plugin_ncupdate/__init__.py
nonebot_plugin_ncupdate/config.py
nonebot_plugin_ncupdate/dialog.py
nonebot_plugin_ncupdate/info.py
nonebot_plugin_ncupdate/mode.json
nonebot_plugin_ncupdate/notice.py
nonebot_plugin_ncupdate/restart.py
nonebot_plugin_ncupdate/sysexec.py
nonebot_plugin_ncupdate/unzip.py
nonebot_plugin_ncupdate/version.py
nonebot_plugin_ncupdate-0.2.9.dist-info/LICENSE
nonebot_plugin_ncupdate-0.2.9.dist-info/METADATA
nonebot_plugin_ncupdate-0.2.9.dist-info/WHEEL
nonebot_plugin_ncupdate-0.2.9.dist-info/RECORD
