Metadata-Version: 2.1
Name: nonebot-plugin-ncupdate
Version: 0.2.9
Summary: A nonebot plugin for update NapCat
Home-page: https://github.com/tianyisama
License: MIT
Author: tianyisama
Requires-Python: >=3.8,<4.0
Classifier: License :: OSI Approved :: MIT License
Classifier: Programming Language :: Python :: 3
Classifier: Programming Language :: Python :: 3.8
Classifier: Programming Language :: Python :: 3.9
Classifier: Programming Language :: Python :: 3.10
Classifier: Programming Language :: Python :: 3.11
Classifier: Programming Language :: Python :: 3.12
Requires-Dist: aiofiles (>=23.2.1)
Requires-Dist: distro (>=1.5.0)
Requires-Dist: httpx (>=0.23.3)
Requires-Dist: nonebot-adapter-onebot (>=2.1.1,<3.0.0)
Requires-Dist: nonebot2 (>=2.2.0,<3.0.0)
Requires-Dist: packaging (>=24.1)
Requires-Dist: psutil (>=5.9.0,<6.0.0)
Project-URL: Repository, https://github.com/tianyisama/nonebot-plugin-ncupdate
